eporner_api/__init__.py
eporner_api/eporner_api.py
eporner_api/modules/__init__.py
eporner_api/modules/consts.py
eporner_api/modules/errors.py
eporner_api/modules/locals.py
eporner_api/modules/progressbar.py
eporner_api/modules/sorting.py
eporner_api/tests/__init__.py
eporner_api/tests/conftest.py
eporner_api/tests/test_category.py
eporner_api/tests/test_pornstar.py
eporner_api/tests/test_search.py
eporner_api/tests/test_video.py
Eporner_API_async-1.8.5.dist-info/LICENSE
Eporner_API_async-1.8.5.dist-info/METADATA
Eporner_API_async-1.8.5.dist-info/WHEEL
Eporner_API_async-1.8.5.dist-info/entry_points.txt
Eporner_API_async-1.8.5.dist-info/top_level.txt
Eporner_API_async-1.8.5.dist-info/RECORD
